tests/__init__.py
tests/test_core.py
tests/test_drawer.py
tests/test_image_source.py
tksss/__init__.py
tksss/core.py
tksss/drawer.py
tksss/image_source.py
tksss-1.0.0.dist-info/METADATA
tksss-1.0.0.dist-info/WHEEL
tksss-1.0.0.dist-info/entry_points.txt
tksss-1.0.0.dist-info/top_level.txt
tksss-1.0.0.dist-info/RECORD
