Metadata-Version: 2.1
Name: tksss
Version: 1.0.0
Summary: This is a test package for uchida
Author: uchida1512
Author-email: uchida1512@gmail.com
Classifier: License :: OSI Approved :: MIT License
Classifier: Programming Language :: Python :: 3
Classifier: Programming Language :: Python :: 3.6
Classifier: Programming Language :: Python :: 3.7
Classifier: Programming Language :: Python :: 3.8
Classifier: Operating System :: OS Independent
Requires-Python: ~=3.8
Requires-Dist: Click (~=7.0)
Requires-Dist: Pillow (~=6.2.1)
Requires-Dist: requests (~=2.28.1)
